README.md
setup.py
cli/__init__.py
cli/cli.py
lol/__init__.py
lol/argparse/__init__.py
lol/argparse/argparse.py
lol/database/__init__.py
lol/database/database.py
lol/database/serializer.py
lol/datatypes/__init__.py
lol/datatypes/array.py
lol/datatypes/interface.py
lol/datatypes/maps.py
lol/datatypes/number.py
lol/datatypes/string.py
lol/prompt/__init__.py
lol/prompt/prompt.py
lol/switch/__init__.py
lol/switch/switch.py
loldb.egg-info/PKG-INFO
loldb.egg-info/SOURCES.txt
loldb.egg-info/dependency_links.txt
loldb.egg-info/entry_points.txt
loldb.egg-info/requires.txt
loldb.egg-info/top_level.txt
project/__init__.py
project/project.py