Metadata-Version: 2.1
Name: loldb
Version: 0.1.5
Summary: A simple json database and other utilities
Home-page: https://github.com/pranavbaburaj/lol
Author: P Pranav Baburaj
Author-email: code-roller@googlegroups.com
License: UNKNOWN
Platform: UNKNOWN
Classifier: Programming Language :: Python :: 3
Classifier: License :: OSI Approved :: MIT License
Classifier: Operating System :: OS Independent
Requires-Python: >=3.6
